CHANGELOG.rst
LICENSE
MANIFEST.in
README.rst
setup.cfg
setup.py
aldryn_wow/__init__.py
aldryn_wow/cms_plugins.py
aldryn_wow/models.py
aldryn_wow/tests.py
aldryn_wow/utils.py
aldryn_wow.egg-info/PKG-INFO
aldryn_wow.egg-info/SOURCES.txt
aldryn_wow.egg-info/dependency_links.txt
aldryn_wow.egg-info/not-zip-safe
aldryn_wow.egg-info/requires.txt
aldryn_wow.egg-info/top_level.txt
aldryn_wow/migrations/0001_initial.py
aldryn_wow/migrations/__init__.py
aldryn_wow/south_migrations/0001_initial.py
aldryn_wow/south_migrations/__init__.py
aldryn_wow/static/aldryn_wow/css/animate.css
aldryn_wow/static/aldryn_wow/js/wow.js
aldryn_wow/templates/aldryn_wow/animation.html
aldryn_wow/templates/aldryn_wow/wow_animation.html